{
   "mixins" : "stonehearth:mixins:item_properties",
   "type": "entity",
   "components" : {
      "unit_info" : {
         "name": "Iron Mail",
         "description": "A full suit of iron armor",
         "icon" : "file(iron_mail.png)"         
      },
      "item" : {
         "category" : "armor"   
      },
      "stonehearth:material" : {
         "tags" : "iron armor heavy_armor"
      },
      "model_variants": {
         "default": {
            "layer": "clothing",
            "models": [
               "file(iron_mail.qb)"
            ]
         },
         "female" : {
            "layer": "clothing",
            "models": [
               "file(iron_mail_female.qb)"
            ]
         }
      },
      "stonehearth:entity_forms" : {
         "iconic_form" : "file(iron_mail_iconic.json)"
      },
      "stonehearth:equipment_piece" : {
         "render_type" : "merge_with_model",
         "slot" : "torso",
         "ilevel" : 6,
         "roles" : "combat",
         "equip_effect" : "/stonehearth/data/effects/level_up"
      }
   },
   "entity_data" : {
      "stonehearth:combat:armor_data" : {
         "base_damage_reduction" : 7
      },
      "stonehearth:net_worth" : {
         "value_in_gold" : 205,
         "rarity" : "common",
         "shop_info" : {
            "buyable" : true,   
            "sellable" : true,
            "shopkeeper_level" : 1,
            "shopkeeper_type" : "caravan"
         }
      }
   }   
}