{
	"type": "animation",
	"frames": [
			{
				"root": {
					"pos": [0,0,0],
					"rot": [1.0,0.0,0.0,0.0]
				},
				"bodyPosition": {
					"pos": [0,0,7.5],
					"rot": [1.0,0.0,0.0,0.0]
				},
				"pelvis": {
					"pos": [0,0,7.5],
					"rot": [1.0,0.0,0.0,0.0]
				},
				"torso": {
					"pos": [0,0,10],
					"rot": [1.0,0.0,0.0,0.0]
				},
				"head": {
					"pos": [0,-1.02572,16.9696],
					"rot": [1.0,0.0,0.0,0.0]
				},
				"leftShoulder": {
					"pos": [3.5,0,14],
					"rot": [1.0,0.0,0.0,0.0]
				},
				"leftArm": {
					"pos": [6.5,-0.5,10],
					"rot": [0.999105,0.0,-0.0422948,0.0]
				},
				"leftHand": {
					"pos": [6.58451,-0.5,9.00358],
					"rot": [0.999105,0.0,-0.0422948,0.0]
				},
				"leftThumb1": {
					"pos": [5.67261,-3.5,7.92264],
					"rot": [0.998907,0.0,0.0467401,0.0]
				},
				"leftThumb2": {
					"pos": [5.48585,-4.5,5.93138],
					"rot": [0.955777,0.290354,0.044722,-0.013586]
				},
				"leftFinger11": {
					"pos": [8.74639,-2.5,7.17976],
					"rot": [0.999117,-0.0228376,-0.0352639,-0.000806057]
				},
				"leftFinger12": {
					"pos": [8.88724,-2.59138,5.18682],
					"rot": [0.995934,-0.0225678,0.0871425,-0.00359191]
				},
				"leftFinger21": {
					"pos": [8.74639,-0.5,7.17976],
					"rot": [0.998417,0.0,0.0562484,0.0]
				},
				"leftFinger22": {
					"pos": [8.52175,-0.5,5.19242],
					"rot": [0.977844,0.0,0.209337,0.0]
				},
				"leftFinger31": {
					"pos": [8.74639,1.5,7.17976],
					"rot": [0.986455,0.0676568,0.149079,-0.0102247]
				},
				"leftFinger32": {
					"pos": [8.16092,1.77306,5.28697],
					"rot": [0.94048,0.0683697,0.332891,0.002751]
				},
				"offHand": {
					"pos": [6.83806,-0.5,6.01431],
					"rot": [0.999105,0.0,-0.0422948,0.0]
				},
				"rightShoulder": {
					"pos": [-3.5,0,14],
					"rot": [1.0,0.0,0.0,0.0]
				},
				"rightArm": {
					"pos": [-6.5,-0.5,10],
					"rot": [0.99928,0.0,0.037933,0.0]
				},
				"rightHand": {
					"pos": [-6.57581,-0.5,9.00288],
					"rot": [0.99928,0.0,0.037933,0.0]
				},
				"rightThumb1": {
					"pos": [-5.6545,-3.5,7.92995],
					"rot": [0.998449,0.0,-0.0556832,0.0]
				},
				"rightThumb2": {
					"pos": [-5.43211,-4.5,5.94235],
					"rot": [0.935209,0.349692,-0.0521563,0.0195022]
				},
				"rightFinger11": {
					"pos": [-8.72168,-2.5,7.16026],
					"rot": [0.999375,-0.0311734,0.0166704,0.000519997]
				},
				"rightFinger12": {
					"pos": [-8.78825,-2.62465,5.16526],
					"rot": [0.985427,-0.0305473,-0.167214,0.00623819]
				},
				"rightFinger21": {
					"pos": [-8.72168,-0.5,7.16026],
					"rot": [0.997457,0.0,-0.0712756,0.0]
				},
				"rightFinger22": {
					"pos": [-8.4373,-0.5,5.18058],
					"rot": [0.939516,0.0,-0.342506,0.0]
				},
				"rightFinger31": {
					"pos": [-8.72168,1.5,7.16026],
					"rot": [0.989873,0.0624973,-0.1274,-0.00386322]
				},
				"rightFinger32": {
					"pos": [-8.21627,1.74549,5.2408],
					"rot": [0.918828,0.0591392,-0.38966,-0.0205764]
				},
				"mainHand": {
					"pos": [-6.80324,-0.5,6.01151],
					"rot": [0.99928,0.0,0.037933,0.0]
				},
				"leftFoot": {
					"pos": [3,-1.5,5],
					"rot": [1.0,0.0,0.0,0.0]
				},
				"rightFoot": {
					"pos": [-3,-1.5,5],
					"rot": [1.0,0.0,0.0,0.0]
				}
			},
			{
				"root": {
					"pos": [0,0,0],
					"rot": [1.0,0.0,0.0,0.0]
				},
				"bodyPosition": {
					"pos": [0,0,7.5],
					"rot": [1.0,0.0,0.0,0.0]
				},
				"pelvis": {
					"pos": [0,0.0558066,7.58438],
					"rot": [1.0,0.0,0.0,0.0]
				},
				"torso": {
					"pos": [0,0.0558066,10.0844],
					"rot": [0.999824,-0.0187355,0.0,0.0]
				},
				"head": {
					"pos": [0,-0.70808,17.0875],
					"rot": [0.999984,0.00528042,0.00176956,-0.000748541]
				},
				"leftShoulder": {
					"pos": [3.5,0.205664,14.0816],
					"rot": [0.999316,-0.0187259,-0.0318964,0.000597699]
				},
				"leftArm": {
					"pos": [6.74898,-0.43637,10.3024],
					"rot": [0.995609,-0.0586122,-0.0729715,-0.0015567]
				},
				"leftHand": {
					"pos": [6.8941,-0.553307,9.31995],
					"rot": [0.994731,-0.0586259,-0.0840955,-0.000901451]
				},
				"leftThumb1": {
					"pos": [6.04048,-3.65753,8.52301],
					"rot": [0.998269,-0.0583134,0.00471607,-0.00611247]
				},
				"leftThumb2": {
					"pos": [6.00857,-4.88339,6.65318],
					"rot": [0.978534,0.205943,0.00294495,-0.00713658]
				},
				"leftFinger11": {
					"pos": [9.1769,-2.75699,7.92977],
					"rot": [0.993124,-0.0880758,-0.0770308,-0.00359682]
				},
				"leftFinger12": {
					"pos": [9.48164,-3.10798,5.98454],
					"rot": [0.9956,-0.0871574,0.0317999,-0.0131863]
				},
				"leftFinger21": {
					"pos": [9.20021,-0.770744,7.69681],
					"rot": [0.998178,-0.0582526,0.0142201,-0.00666738]
				},
				"leftFinger22": {
					"pos": [9.14188,-1.00295,5.71119],
					"rot": [0.986553,-0.0567643,0.152561,-0.0146843]
				},
				"leftFinger31": {
					"pos": [9.22351,1.2155,7.46384],
					"rot": [0.994013,0.014927,0.106399,-0.0198765]
				},
				"leftFinger32": {
					"pos": [8.80165,1.28331,5.51002],
					"rot": [0.963237,0.0179762,0.267501,-0.0171683]
				},
				"offHand": {
					"pos": [7.3957,-0.903664,6.383],
					"rot": [0.994731,-0.058626,-0.0840955,-0.000901452]
				},
				"rightShoulder": {
					"pos": [-3.5,0.205664,14.0816],
					"rot": [0.999667,-0.0106763,0.0234659,-0.00062889]
				},
				"rightArm": {
					"pos": [-6.68479,-0.37421,10.2383],
					"rot": [0.997503,-0.0349251,0.0613764,0.00046005]
				},
				"rightHand": {
					"pos": [-6.8072,-0.443942,9.24826],
					"rot": [0.996612,-0.0349281,0.0744545,1.92845e-006]
				},
				"rightThumb1": {
					"pos": [-5.95108,-3.51144,8.32224],
					"rot": [0.999208,-0.0347749,-0.0190723,0.0032683]
				},
				"rightThumb2": {
					"pos": [-5.86919,-4.64774,6.39815],
					"rot": [0.961382,0.274536,-0.0171397,0.00898127]
				},
				"rightFinger11": {
					"pos": [-9.07143,-2.56791,7.71136],
					"rot": [0.996002,-0.0717225,0.0531847,0.00270896]
				},
				"rightFinger12": {
					"pos": [-9.28254,-2.85423,5.74325],
					"rot": [0.991832,-0.0703853,-0.105441,0.0140489]
				},
				"rightFinger21": {
					"pos": [-9.08184,-0.572787,7.57212],
					"rot": [0.998788,-0.0347196,-0.034681,0.00381121]
				},
				"rightFinger22": {
					"pos": [-8.94276,-0.710969,5.58175],
					"rot": [0.95986,-0.032728,-0.278297,0.0122003]
				},
				"rightFinger31": {
					"pos": [-9.09225,1.42233,7.43288],
					"rot": [0.995454,0.0278955,-0.0910628,-0.000385409]
				},
				"rightFinger32": {
					"pos": [-8.72961,1.53327,5.46916],
					"rot": [0.946513,0.0270309,-0.321457,-0.00690184]
				},
				"mainHand": {
					"pos": [-7.25242,-0.652802,6.28884],
					"rot": [0.996613,-0.0349281,0.0744545,1.92855e-006]
				},
				"leftFoot": {
					"pos": [3,-1.5,5],
					"rot": [1.0,0.0,0.0,0.0]
				},
				"rightFoot": {
					"pos": [-3,-1.5,5],
					"rot": [1.0,0.0,0.0,0.0]
				}
			},
			{
				"root": {
					"pos": [0,0,0],
					"rot": [1.0,0.0,0.0,0.0]
				},
				"bodyPosition": {
					"pos": [0,0,7.5],
					"rot": [1.0,0.0,0.0,0.0]
				},
				"pelvis": {
					"pos": [0,0.178581,7.77001],
					"rot": [1.0,0.0,0.0,0.0]
				},
				"torso": {
					"pos": [0,0.178581,10.27],
					"rot": [0.998203,-0.0599211,0.0,0.0]
				},
				"head": {
					"pos": [0,-0.00601757,17.3123],
					"rot": [0.999838,0.0169048,0.00541255,-0.00291652]
				},
				"leftShoulder": {
					"pos": [3.5,0.657089,14.2413],
					"rot": [0.993004,-0.059609,-0.101743,0.00610754]
				},
				"leftArm": {
					"pos": [7.24883,-0.235108,11.0163],
					"rot": [0.972642,-0.185212,-0.139903,-0.00956396]
				},
				"leftHand": {
					"pos": [7.51744,-0.598074,10.1241],
					"rot": [0.967016,-0.185436,-0.174597,-0.00293435]
				},
				"leftThumb1": {
					"pos": [6.70373,-3.81045,9.98792],
					"rot": [0.978713,-0.18444,-0.0878918,-0.0194167]
				},
				"leftThumb2": {
					"pos": [6.96306,-5.47054,8.51251],
					"rot": [0.995823,0.0153269,-0.0899998,-0.0014191]
				},
				"leftFinger11": {
					"pos": [9.92779,-3.06166,9.77634],
					"rot": [0.959007,-0.228325,-0.167443,-0.0117023]
				},
				"leftFinger12": {
					"pos": [10.5594,-3.94537,8.09702],
					"rot": [0.969344,-0.226652,-0.0900167,-0.0299703]
				},
				"leftFinger21": {
					"pos": [10.0686,-1.19925,9.06111],
					"rot": [0.979506,-0.184247,-0.0785698,-0.0211718]
				},
				"leftFinger22": {
					"pos": [10.3609,-1.92778,7.22159],
					"rot": [0.982341,-0.181004,0.0247329,-0.0404044]
				},
				"leftFinger31": {
					"pos": [10.2095,0.663175,8.34588],
					"rot": [0.994139,-0.100189,0.0102419,-0.0392932]
				},
				"leftFinger32": {
					"pos": [10.153,0.266375,6.38646],
					"rot": [0.987343,-0.0954129,0.116497,-0.0497822]
				},
				"offHand": {
					"pos": [8.5272,-1.67706,7.51332],
					"rot": [0.967016,-0.185436,-0.174597,-0.00293435]
				},
				"rightShoulder": {
					"pos": [-3.5,0.657089,14.2413],
					"rot": [0.996597,-0.0340711,0.0747784,-0.00642725]
				},
				"rightArm": {
					"pos": [-7.068,-0.0557866,10.7756],
					"rot": [0.987405,-0.110947,0.112788,0.00106164]
				},
				"rightHand": {
					"pos": [-7.2905,-0.275124,9.82564],
					"rot": [0.981803,-0.110893,0.15412,-0.00359468]
				},
				"rightThumb1": {
					"pos": [-6.56009,-3.45915,9.25248],
					"rot": [0.991913,-0.110744,0.0616294,0.00679154]
				},
				"rightThumb2": {
					"pos": [-6.77448,-4.87559,7.53559],
					"rot": [0.992782,0.102662,0.0616645,-0.00646572]
				},
				"rightFinger11": {
					"pos": [-9.74805,-2.57669,9.01122],
					"rot": [0.978161,-0.159547,0.133109,0.00535773]
				},
				"rightFinger12": {
					"pos": [-10.2654,-3.20379,7.18392],
					"rot": [0.986667,-0.158148,0.0316868,0.0217568]
				},
				"rightFinger21": {
					"pos": [-9.80229,-0.62593,8.57351],
					"rot": [0.992755,-0.110624,0.0461248,0.0085209]
				},
				"rightFinger22": {
					"pos": [-9.98169,-1.06679,6.63097],
					"rot": [0.984997,-0.107316,-0.132175,0.0281689]
				},
				"rightFinger31": {
					"pos": [-9.85654,1.32483,8.13579],
					"rot": [0.99876,-0.0485181,-0.0105423,0.00363285]
				},
				"rightFinger32": {
					"pos": [-9.81372,1.13115,6.14565],
					"rot": [0.985167,-0.0473761,-0.164556,0.0110772]
				},
				"mainHand": {
					"pos": [-8.20079,-0.925053,7.04194],
					"rot": [0.981803,-0.110893,0.15412,-0.00359468]
				},
				"leftFoot": {
					"pos": [3,-1.5,5],
					"rot": [1.0,0.0,0.0,0.0]
				},
				"rightFoot": {
					"pos": [-3,-1.5,5],
					"rot": [1.0,0.0,0.0,0.0]
				}
			},
			{
				"root": {
					"pos": [0,0,0],
					"rot": [1.0,0.0,0.0,0.0]
				},
				"bodyPosition": {
					"pos": [0,0,7.5],
					"rot": [1.0,0.0,0.0,0.0]
				},
				"pelvis": {
					"pos": [0,0.301356,7.95565],
					"rot": [1.0,0.0,0.0,0.0]
				},
				"torso": {
					"pos": [0,0.301356,10.4556],
					"rot": [0.994886,-0.101005,0.0,0.0]
				},
				"head": {
					"pos": [0,0.697298,17.4892],
					"rot": [0.999539,0.0285378,0.00863098,-0.00575753]
				},
				"leftShoulder": {
					"pos": [3.5,1.10526,14.374],
					"rot": [0.980155,-0.0995094,-0.170572,0.0173172]
				},
				"leftArm": {
					"pos": [7.67491,0.0625011,11.7793],
					"rot": [0.929466,-0.305475,-0.20546,-0.0237701]
				},
				"leftHand": {
					"pos": [8.04233,-0.515123,11.0503],
					"rot": [0.915379,-0.306352,-0.261154,-0.00529941]
				},
				"leftThumb1": {
					"pos": [7.14451,-3.66578,11.5674],
					"rot": [0.934979,-0.304667,-0.178699,-0.0325275]
				},
				"leftThumb2": {
					"pos": [7.60348,-5.6407,10.6245],
					"rot": [0.96792,-0.173605,-0.181471,-0.00772088]
				},
				"leftFinger11": {
					"pos": [10.3797,-2.96624,11.7774],
					"rot": [0.897379,-0.360242,-0.253823,-0.0225674]
				},
				"leftFinger12": {
					"pos": [11.2583,-4.28224,10.5542],
					"rot": [0.909189,-0.358616,-0.207583,-0.0409671]
				},
				"leftFinger21": {
					"pos": [10.7191,-1.34175,10.6613],
					"rot": [0.936638,-0.304343,-0.169789,-0.0354267]
				},
				"leftFinger22": {
					"pos": [11.3121,-2.50605,9.14708],
					"rot": [0.946349,-0.301049,-0.10268,-0.0570026]
				},
				"leftFinger31": {
					"pos": [11.0586,0.282726,9.54509],
					"rot": [0.971854,-0.211684,-0.086888,-0.0560375]
				},
				"leftFinger32": {
					"pos": [11.3489,-0.559655,7.75453],
					"rot": [0.974984,-0.208616,-0.038167,-0.0665559]
				},
				"offHand": {
					"pos": [9.46692,-2.206,9.02266],
					"rot": [0.915379,-0.306352,-0.261154,-0.00529941]
				},
				"rightShoulder": {
					"pos": [-3.5,1.10526,14.374],
					"rot": [0.990326,-0.0571744,0.125113,-0.0182294]
				},
				"rightArm": {
					"pos": [-7.41454,0.325378,11.3215],
					"rot": [0.968982,-0.184994,0.163858,0.00109317]
				},
				"rightHand": {
					"pos": [-7.73169,-0.0334915,10.4436],
					"rot": [0.954956,-0.184607,0.232022,-0.0120016]
				},
				"rightThumb1": {
					"pos": [-7.09899,-3.28375,10.2552],
					"rot": [0.97247,-0.184921,0.1417,0.00531501]
				},
				"rightThumb2": {
					"pos": [-7.58351,-4.93763,8.83045],
					"rot": [0.987302,-0.0716105,0.141368,-0.0110514]
				},
				"rightFinger11": {
					"pos": [-10.2854,-2.37345,10.389],
					"rot": [0.946352,-0.244028,0.211759,0.00507914]
				},
				"rightFinger12": {
					"pos": [-11.0821,-3.3015,8.80657],
					"rot": [0.955262,-0.24352,0.167031,0.0165467]
				},
				"rightFinger21": {
					"pos": [-10.4109,-0.510345,9.67269],
					"rot": [0.974565,-0.184815,0.12649,0.00820345]
				},
				"rightFinger22": {
					"pos": [-10.8979,-1.23495,7.87332],
					"rot": [0.982598,-0.182736,0.0166251,0.0288357]
				},
				"rightFinger31": {
					"pos": [-10.5364,1.35276,8.95639],
					"rot": [0.989779,-0.124259,0.0699281,0.00267339]
				},
				"rightFinger32": {
					"pos": [-10.8119,0.860055,7.03771],
					"rot": [0.992241,-0.123725,-0.00316861,0.011819]
				},
				"mainHand": {
					"pos": [-9.07441,-1.07454,7.9711],
					"rot": [0.954956,-0.184607,0.232022,-0.0120016]
				},
				"leftFoot": {
					"pos": [3,-1.5,5],
					"rot": [1.0,0.0,0.0,0.0]
				},
				"rightFoot": {
					"pos": [-3,-1.5,5],
					"rot": [1.0,0.0,0.0,0.0]
				}
			},
			{
				"root": {
					"pos": [0,0,0],
					"rot": [1.0,0.0,0.0,0.0]
				},
				"bodyPosition": {
					"pos": [0,0,7.5],
					"rot": [1.0,0.0,0.0,0.0]
				},
				"pelvis": {
					"pos": [0,0.357162,8.04003],
					"rot": [1.0,0.0,0.0,0.0]
				},
				"torso": {
					"pos": [0,0.357162,10.54],
					"rot": [0.992819,-0.119627,0.0,0.0]
				},
				"head": {
					"pos": [0,1.01633,17.5538],
					"rot": [0.999352,0.0338277,0.00992824,-0.00725458]
				},
				"leftShoulder": {
					"pos": [3.5,1.30731,14.4255],
					"rot": [0.97219,-0.117141,-0.201335,0.0242593]
				},
				"leftArm": {
					"pos": [7.84188,0.232636,12.1357],
					"rot": [0.903564,-0.357064,-0.234605,-0.0322264]
				},
				"leftHand": {
					"pos": [8.24282,-0.427744,11.5008],
					"rot": [0.884483,-0.358454,-0.29859,-0.006622]
				},
				"leftThumb1": {
					"pos": [7.26734,-3.49694,12.2936],
					"rot": [0.907536,-0.356444,-0.218734,-0.0384791]
				},
				"leftThumb2": {
					"pos": [7.78074,-5.56748,11.6233],
					"rot": [0.940768,-0.256182,-0.221613,-0.0145923]
				},
				"leftFinger11": {
					"pos": [10.4814,-2.78501,12.6976],
					"rot": [0.860908,-0.416263,-0.291122,-0.0284618]
				},
				"leftFinger12": {
					"pos": [11.4365,-4.25161,11.7297],
					"rot": [0.871337,-0.414883,-0.258238,-0.0442399]
				},
				"leftFinger21": {
					"pos": [10.9329,-1.29914,11.4373],
					"rot": [0.909578,-0.356062,-0.210084,-0.041871]
				},
				"leftFinger22": {
					"pos": [11.6376,-2.62979,10.1209],
					"rot": [0.91988,-0.353172,-0.159019,-0.0616674]
				},
				"leftFinger31": {
					"pos": [11.3845,0.186723,10.177],
					"rot": [0.954558,-0.260395,-0.130659,-0.062786]
				},
				"leftFinger32": {
					"pos": [11.818,-0.840338,8.5165],
					"rot": [0.957428,-0.258807,-0.107633,-0.0690386]
				},
				"offHand": {
					"pos": [9.81317,-2.34189,9.80668],
					"rot": [0.884484,-0.358454,-0.29859,-0.006622]
				},
				"rightShoulder": {
					"pos": [-3.5,1.30731,14.4255],
					"rot": [0.986425,-0.0675257,0.14749,-0.0255423]
				},
				"rightArm": {
					"pos": [-7.5585,0.520712,11.569],
					"rot": [0.957944,-0.217723,0.186921,0.000917833]
				},
				"rightHand": {
					"pos": [-7.91622,0.103236,10.7337],
					"rot": [0.938898,-0.217034,0.266584,-0.0173409]
				},
				"rightThumb1": {
					"pos": [-7.31761,-3.15891,10.7273],
					"rot": [0.959713,-0.217704,0.177612,0.00303154]
				},
				"rightThumb2": {
					"pos": [-7.91365,-4.90199,9.45989],
					"rot": [0.972685,-0.149429,0.177383,-0.0095111]
				},
				"rightFinger11": {
					"pos": [-10.4807,-2.20719,11.0261],
					"rot": [0.927449,-0.280863,0.246857,0.004019]
				},
				"rightFinger12": {
					"pos": [-11.392,-3.2531,9.58536],
					"rot": [0.932548,-0.280711,0.226835,0.0100638]
				},
				"rightFinger21": {
					"pos": [-10.647,-0.396807,10.1925],
					"rot": [0.962371,-0.21763,0.162597,0.00643244]
				},
				"rightFinger22": {
					"pos": [-11.2673,-1.23875,8.48769],
					"rot": [0.972405,-0.216387,0.0838145,0.0241052]
				},
				"rightFinger31": {
					"pos": [-10.8133,1.41358,9.35891],
					"rot": [0.981692,-0.158114,0.106213,0.000623878]
				},
				"rightFinger32": {
					"pos": [-11.23,0.792433,7.50403],
					"rot": [0.984935,-0.157984,0.0700169,0.00644175]
				},
				"mainHand": {
					"pos": [-9.44057,-1.09166,8.44271],
					"rot": [0.938898,-0.217034,0.266584,-0.0173409]
				},
				"leftFoot": {
					"pos": [3,-1.5,5],
					"rot": [1.0,0.0,0.0,0.0]
				},
				"rightFoot": {
					"pos": [-3,-1.5,5],
					"rot": [1.0,0.0,0.0,0.0]
				}
			},
			{
				"root": {
					"pos": [0,0,0],
					"rot": [1.0,0.0,0.0,0.0]
				},
				"bodyPosition": {
					"pos": [0,0,7.5],
					"rot": [1.0,0.0,0.0,0.0]
				},
				"pelvis": {
					"pos": [0,0.330706,8.00003],
					"rot": [1.0,0.0,0.0,0.0]
				},
				"torso": {
					"pos": [0,0.330706,10.5],
					"rot": [0.993842,-0.110804,0.0,0.0]
				},
				"head": {
					"pos": [0,0.865181,17.5244],
					"rot": [0.999445,0.0313197,0.0093271,-0.00652957]
				},
				"leftShoulder": {
					"pos": [3.5,1.21168,14.4018],
					"rot": [0.97613,-0.108829,-0.186799,0.0208262]
				},
				"leftArm": {
					"pos": [7.76489,0.149178,11.9663],
					"rot": [0.916312,-0.332883,-0.220847,-0.0280642]
				},
				"leftHand": {
					"pos": [8.15093,-0.473267,11.2854],
					"rot": [0.899685,-0.334011,-0.281014,-0.00596887]
				},
				"leftThumb1": {
					"pos": [7.21521,-3.58502,11.9498],
					"rot": [0.921114,-0.332156,-0.199876,-0.0356544]
				},
				"leftThumb2": {
					"pos": [7.70581,-5.61414,11.1486],
					"rot": [0.954734,-0.217396,-0.202731,-0.0110239]
				},
				"leftFinger11": {
					"pos": [10.4413,-2.88163,12.2621],
					"rot": [0.878826,-0.390056,-0.273617,-0.0255905]
				},
				"leftFinger12": {
					"pos": [11.3632,-4.28081,11.1702],
					"rot": [0.890065,-0.388543,-0.234492,-0.0428116]
				},
				"leftFinger21": {
					"pos": [10.8382,-1.32803,11.0668],
					"rot": [0.922975,-0.331801,-0.191097,-0.0388152]
				},
				"leftFinger22": {
					"pos": [11.4922,-2.58267,9.65328],
					"rot": [0.933192,-0.328692,-0.132488,-0.0596704]
				},
				"leftFinger31": {
					"pos": [11.2352,0.225578,9.87153],
					"rot": [0.963302,-0.237485,-0.109965,-0.0596508]
				},
				"leftFinger32": {
					"pos": [11.6022,-0.71574,8.14549],
					"rot": [0.966665,-0.235158,-0.0748452,-0.0682514]
				},
				"offHand": {
					"pos": [9.65591,-2.28636,9.42863],
					"rot": [0.899685,-0.334011,-0.281014,-0.00596886]
				},
				"rightShoulder": {
					"pos": [-3.5,1.21168,14.4018],
					"rot": [0.988356,-0.0626322,0.136927,-0.0219256]
				},
				"rightArm": {
					"pos": [-7.49136,0.426352,11.4518],
					"rot": [0.96338,-0.20229,0.176001,0.00101577]
				},
				"rightHand": {
					"pos": [-7.83006,0.0362301,10.5956],
					"rot": [0.946805,-0.201758,0.250275,-0.0146949]
				},
				"rightThumb1": {
					"pos": [-7.21613,-3.22175,10.5026],
					"rot": [0.966061,-0.202248,0.160636,0.00423732]
				},
				"rightThumb2": {
					"pos": [-7.76028,-4.92416,9.15879],
					"rot": [0.980546,-0.112731,0.160346,-0.0105234]
				},
				"rightFinger11": {
					"pos": [-10.392,-2.29184,10.7238],
					"rot": [0.936749,-0.26354,0.230277,0.00459248]
				},
				"rightFinger12": {
					"pos": [-11.25,-3.28355,9.21374],
					"rot": [0.943959,-0.263237,0.198661,0.0134482]
				},
				"rightFinger21": {
					"pos": [-10.5384,-0.455528,9.945],
					"rot": [0.968453,-0.202157,0.145523,0.0073966]
				},
				"rightFinger22": {
					"pos": [-11.0961,-1.24295,8.19318],
					"rot": [0.977941,-0.200518,0.0520487,0.0267348]
				},
				"rightFinger31": {
					"pos": [-10.6847,1.38078,9.16619],
					"rot": [0.985834,-0.142123,0.0890448,0.00171916]
				},
				"rightFinger32": {
					"pos": [-11.0348,0.819733,7.2787],
					"rot": [0.989214,-0.14182,0.0353999,0.0094314]
				},
				"mainHand": {
					"pos": [-9.26962,-1.08786,8.2157],
					"rot": [0.946805,-0.201758,0.250275,-0.0146949]
				},
				"leftFoot": {
					"pos": [3,-1.5,5],
					"rot": [1.0,0.0,0.0,0.0]
				},
				"rightFoot": {
					"pos": [-3,-1.5,5],
					"rot": [1.0,0.0,0.0,0.0]
				}
			},
			{
				"root": {
					"pos": [0,0,0],
					"rot": [1.0,0.0,0.0,0.0]
				},
				"bodyPosition": {
					"pos": [0,0,7.5],
					"rot": [1.0,0.0,0.0,0.0]
				},
				"pelvis": {
					"pos": [0,0.264565,7.90002],
					"rot": [1.0,0.0,0.0,0.0]
				},
				"torso": {
					"pos": [0,0.264565,10.4],
					"rot": [0.996058,-0.0887085,0.0,0.0]
				},
				"head": {
					"pos": [0,0.486643,17.4412],
					"rot": [0.999645,0.0250511,0.00771674,-0.00483912]
				},
				"leftShoulder": {
					"pos": [3.5,0.971435,14.3371],
					"rot": [0.984684,-0.0876955,-0.150094,0.0133674]
				},
				"leftArm": {
					"pos": [7.5555,-0.0375128,11.5469],
					"rot": [0.944444,-0.270321,-0.186003,-0.0188727]
				},
				"leftHand": {
					"pos": [7.89664,-0.555138,10.7623],
					"rot": [0.933266,-0.270941,-0.235766,-0.00452825]
				},
				"leftThumb1": {
					"pos": [7.03683,-3.74172,11.0885],
					"rot": [0.950537,-0.269464,-0.15182,-0.0286096]
				},
				"leftThumb2": {
					"pos": [7.44703,-5.63678,9.97471],
					"rot": [0.980949,-0.117775,-0.154425,-0.00455872]
				},
				"leftFinger11": {
					"pos": [10.277,-3.03852,11.1704],
					"rot": [0.918605,-0.321853,-0.228502,-0.0190137]
				},
				"leftFinger12": {
					"pos": [11.0921,-4.23852,9.79365],
					"rot": [0.930636,-0.320137,-0.173106,-0.0382452]
				},
				"leftFinger21": {
					"pos": [10.5494,-1.33224,10.1633],
					"rot": [0.95194,-0.269179,-0.142763,-0.0311738]
				},
				"leftFinger22": {
					"pos": [11.0595,-2.37501,8.53463],
					"rot": [0.960398,-0.265752,-0.0648622,-0.0529649]
				},
				"leftFinger31": {
					"pos": [10.8219,0.374046,9.15611],
					"rot": [0.980839,-0.178825,-0.0578348,-0.0513001]
				},
				"leftFinger32": {
					"pos": [11.0121,-0.339416,7.2974],
					"rot": [0.982509,-0.17498,0.00811244,-0.0631841]
				},
				"offHand": {
					"pos": [9.20947,-2.0787,8.53623],
					"rot": [0.933266,-0.270941,-0.235766,-0.00452825]
				},
				"rightShoulder": {
					"pos": [-3.5,0.971435,14.3371],
					"rot": [0.99254,-0.0502936,0.110172,-0.01407]
				},
				"rightArm": {
					"pos": [-7.31487,0.204251,11.1577],
					"rot": [0.975359,-0.163073,0.148598,0.00114384]
				},
				"rightHand": {
					"pos": [-7.60437,-0.114197,10.2551],
					"rot": [0.96424,-0.162829,0.208922,-0.00899201]
				},
				"rightThumb1": {
					"pos": [-6.94557,-3.35027,9.94873],
					"rot": [0.979552,-0.162956,0.117833,0.0062747]
				},
				"rightThumb2": {
					"pos": [-7.35247,-4.93853,8.42826],
					"rot": [0.99282,-0.0196184,0.117502,-0.0108278]
				},
				"rightFinger11": {
					"pos": [-10.1397,-2.45757,9.9712],
					"rot": [0.957315,-0.219166,0.188375,0.00546323]
				},
				"rightFinger12": {
					"pos": [-10.8563,-3.30093,8.30528],
					"rot": [0.967383,-0.218371,0.12691,0.0194359]
				},
				"rightFinger21": {
					"pos": [-10.2411,-0.563951,9.33566],
					"rot": [0.981273,-0.162838,0.102515,0.00881985]
				},
				"rightFinger22": {
					"pos": [-10.6377,-1.20672,7.48377],
					"rot": [0.986217,-0.160248,-0.0279525,0.0302442]
				},
				"rightFinger31": {
					"pos": [-10.3425,1.32967,8.70013],
					"rot": [0.993749,-0.10171,0.0458804,0.00347765]
				},
				"rightFinger32": {
					"pos": [-10.5235,0.924737,6.74993],
					"rot": [0.993467,-0.100881,-0.0516373,0.0134193]
				},
				"mainHand": {
					"pos": [-8.82185,-1.04496,7.67604],
					"rot": [0.964239,-0.162829,0.208922,-0.00899201]
				},
				"leftFoot": {
					"pos": [3,-1.5,5],
					"rot": [1.0,0.0,0.0,0.0]
				},
				"rightFoot": {
					"pos": [-3,-1.5,5],
					"rot": [1.0,0.0,0.0,0.0]
				}
			},
			{
				"root": {
					"pos": [0,0,0],
					"rot": [1.0,0.0,0.0,0.0]
				},
				"bodyPosition": {
					"pos": [0,0,7.5],
					"rot": [1.0,0.0,0.0,0.0]
				},
				"pelvis": {
					"pos": [0,0.178581,7.77001],
					"rot": [1.0,0.0,0.0,0.0]
				},
				"torso": {
					"pos": [0,0.178581,10.27],
					"rot": [0.998203,-0.0599211,0.0,0.0]
				},
				"head": {
					"pos": [0,-0.00601757,17.3123],
					"rot": [0.999838,0.0169048,0.00541255,-0.00291652]
				},
				"leftShoulder": {
					"pos": [3.5,0.657089,14.2413],
					"rot": [0.993004,-0.059609,-0.101743,0.00610754]
				},
				"leftArm": {
					"pos": [7.24883,-0.235108,11.0163],
					"rot": [0.972642,-0.185212,-0.139903,-0.00956396]
				},
				"leftHand": {
					"pos": [7.51744,-0.598074,10.1241],
					"rot": [0.967016,-0.185436,-0.174597,-0.00293435]
				},
				"leftThumb1": {
					"pos": [6.70373,-3.81045,9.98792],
					"rot": [0.978713,-0.18444,-0.0878918,-0.0194167]
				},
				"leftThumb2": {
					"pos": [6.96306,-5.47054,8.51251],
					"rot": [0.995823,0.0153269,-0.0899998,-0.0014191]
				},
				"leftFinger11": {
					"pos": [9.92779,-3.06166,9.77634],
					"rot": [0.959007,-0.228325,-0.167443,-0.0117023]
				},
				"leftFinger12": {
					"pos": [10.5594,-3.94537,8.09702],
					"rot": [0.969344,-0.226652,-0.0900167,-0.0299703]
				},
				"leftFinger21": {
					"pos": [10.0686,-1.19925,9.06111],
					"rot": [0.979506,-0.184247,-0.0785698,-0.0211718]
				},
				"leftFinger22": {
					"pos": [10.3609,-1.92778,7.22159],
					"rot": [0.982341,-0.181004,0.0247329,-0.0404044]
				},
				"leftFinger31": {
					"pos": [10.2095,0.663175,8.34588],
					"rot": [0.994139,-0.100189,0.0102419,-0.0392932]
				},
				"leftFinger32": {
					"pos": [10.153,0.266375,6.38646],
					"rot": [0.987343,-0.0954129,0.116497,-0.0497822]
				},
				"offHand": {
					"pos": [8.5272,-1.67706,7.51332],
					"rot": [0.967016,-0.185436,-0.174597,-0.00293435]
				},
				"rightShoulder": {
					"pos": [-3.5,0.657089,14.2413],
					"rot": [0.996597,-0.0340711,0.0747784,-0.00642725]
				},
				"rightArm": {
					"pos": [-7.068,-0.0557866,10.7756],
					"rot": [0.987405,-0.110947,0.112788,0.00106164]
				},
				"rightHand": {
					"pos": [-7.2905,-0.275124,9.82564],
					"rot": [0.981803,-0.110893,0.15412,-0.00359468]
				},
				"rightThumb1": {
					"pos": [-6.56009,-3.45915,9.25248],
					"rot": [0.991913,-0.110744,0.0616294,0.00679154]
				},
				"rightThumb2": {
					"pos": [-6.77448,-4.87559,7.53559],
					"rot": [0.992782,0.102662,0.0616645,-0.00646572]
				},
				"rightFinger11": {
					"pos": [-9.74805,-2.57669,9.01122],
					"rot": [0.978161,-0.159547,0.133109,0.00535773]
				},
				"rightFinger12": {
					"pos": [-10.2654,-3.20379,7.18392],
					"rot": [0.986667,-0.158148,0.0316868,0.0217568]
				},
				"rightFinger21": {
					"pos": [-9.80229,-0.62593,8.57351],
					"rot": [0.992755,-0.110624,0.0461248,0.0085209]
				},
				"rightFinger22": {
					"pos": [-9.98169,-1.06679,6.63097],
					"rot": [0.984997,-0.107316,-0.132175,0.0281689]
				},
				"rightFinger31": {
					"pos": [-9.85654,1.32483,8.13579],
					"rot": [0.99876,-0.0485181,-0.0105423,0.00363285]
				},
				"rightFinger32": {
					"pos": [-9.81372,1.13115,6.14565],
					"rot": [0.985167,-0.0473761,-0.164556,0.0110772]
				},
				"mainHand": {
					"pos": [-8.20079,-0.925053,7.04194],
					"rot": [0.981803,-0.110893,0.15412,-0.00359468]
				},
				"leftFoot": {
					"pos": [3,-1.5,5],
					"rot": [1.0,0.0,0.0,0.0]
				},
				"rightFoot": {
					"pos": [-3,-1.5,5],
					"rot": [1.0,0.0,0.0,0.0]
				}
			},
			{
				"root": {
					"pos": [0,0,0],
					"rot": [1.0,0.0,0.0,0.0]
				},
				"bodyPosition": {
					"pos": [0,0,7.5],
					"rot": [1.0,0.0,0.0,0.0]
				},
				"pelvis": {
					"pos": [0,0.0925977,7.64001],
					"rot": [1.0,0.0,0.0,0.0]
				},
				"torso": {
					"pos": [0,0.0925977,10.14],
					"rot": [0.999517,-0.0310838,0.0,0.0]
				},
				"head": {
					"pos": [0,-0.498063,17.1599],
					"rot": [0.999957,0.00876281,0.00289998,-0.00132427]
				},
				"leftShoulder": {
					"pos": [3.5,0.341148,14.1323],
					"rot": [0.998116,-0.0310403,-0.0528924,0.00164489]
				},
				"leftArm": {
					"pos": [6.90595,-0.385343,10.5099],
					"rot": [0.990913,-0.0969905,-0.0931286,-0.00329734]
				},
				"leftHand": {
					"pos": [7.08987,-0.578175,9.54605],
					"rot": [0.989016,-0.097035,-0.11149,-0.00149799]
				},
				"leftThumb1": {
					"pos": [6.26118,-3.73261,8.94373],
					"rot": [0.995012,-0.0965172,-0.0230783,-0.010123]
				},
				"leftThumb2": {
					"pos": [6.32452,-5.09885,7.17473],
					"rot": [0.988477,0.149259,-0.0248511,-0.00418403]
				},
				"leftFinger11": {
					"pos": [9.43143,-2.8877,8.45828],
					"rot": [0.985892,-0.130703,-0.104402,-0.00574177]
				},
				"leftFinger12": {
					"pos": [9.84014,-3.40553,6.57021],
					"rot": [0.991393,-0.129465,-0.00483656,-0.0188425]
				},
				"leftFinger21": {
					"pos": [9.48063,-0.925372,8.07507],
					"rot": [0.995187,-0.0964164,-0.013604,-0.0110415]
				},
				"leftFinger22": {
					"pos": [9.53052,-1.30978,6.113],
					"rot": [0.988668,-0.0941948,0.114534,-0.0233531]
				},
				"leftFinger31": {
					"pos": [9.52983,1.03696,7.69186],
					"rot": [0.996431,-0.0197754,0.0778423,-0.0259673]
				},
				"leftFinger32": {
					"pos": [9.21751,0.966222,5.71767],
					"rot": [0.974252,-0.0157548,0.223085,-0.0285859]
				},
				"offHand": {
					"pos": [7.7506,-1.15499,6.67712],
					"rot": [0.989016,-0.097035,-0.11149,-0.00149799]
				},
				"rightShoulder": {
					"pos": [-3.5,0.341148,14.1323],
					"rot": [0.999085,-0.0177056,0.0389053,-0.00173078]
				},
				"rightArm": {
					"pos": [-6.80314,-0.285003,10.3977],
					"rot": [0.995366,-0.0578513,0.0768099,0.000699768]
				},
				"rightHand": {
					"pos": [-6.95597,-0.400277,9.41618],
					"rot": [0.993459,-0.0578528,0.0984528,-0.000559355]
				},
				"rightThumb1": {
					"pos": [-6.1402,-3.50753,8.59188],
					"rot": [0.998312,-0.0576516,0.00511579,0.00485334]
				},
				"rightThumb2": {
					"pos": [-6.14923,-4.73116,6.72034],
					"rot": [0.974618,0.223765,0.00626872,0.00322946]
				},
				"rightFinger11": {
					"pos": [-9.288,-2.59156,8.08956],
					"rot": [0.99215,-0.0982872,0.0772171,0.00381465]
				},
				"rightFinger12": {
					"pos": [-9.59295,-2.9828,6.15205],
					"rot": [0.993064,-0.0967502,-0.0644138,0.0177292]
				},
				"rightFinger21": {
					"pos": [-9.30856,-0.604949,7.85944],
					"rot": [0.99827,-0.0575687,-0.0104819,0.00575346]
				},
				"rightFinger22": {
					"pos": [-9.26538,-0.834584,5.87314],
					"rot": [0.970252,-0.0547931,-0.235083,0.0185735]
				},
				"rightFinger31": {
					"pos": [-9.32912,1.38166,7.62933],
					"rot": [0.99774,0.00500434,-0.0669899,0.00134383]
				},
				"rightFinger32": {
					"pos": [-9.06179,1.40199,5.64738],
					"rot": [0.961353,0.00517502,-0.275271,0.000261614]
				},
				"mainHand": {
					"pos": [-7.54302,-0.744793,6.49442],
					"rot": [0.993459,-0.0578528,0.0984528,-0.000559355]
				},
				"leftFoot": {
					"pos": [3,-1.5,5],
					"rot": [1.0,0.0,0.0,0.0]
				},
				"rightFoot": {
					"pos": [-3,-1.5,5],
					"rot": [1.0,0.0,0.0,0.0]
				}
			},
			{
				"root": {
					"pos": [0,0,0],
					"rot": [1.0,0.0,0.0,0.0]
				},
				"bodyPosition": {
					"pos": [0,0,7.5],
					"rot": [1.0,0.0,0.0,0.0]
				},
				"pelvis": {
					"pos": [0,0.0264565,7.54],
					"rot": [1.0,0.0,0.0,0.0]
				},
				"torso": {
					"pos": [0,0.0264565,10.04],
					"rot": [0.999961,-0.0088824,0.0,0.0]
				},
				"head": {
					"pos": [0,-0.875291,17.0267],
					"rot": [0.999996,0.00250302,0.000846667,-0.000335914]
				},
				"leftShoulder": {
					"pos": [3.5,0.0975129,14.0394],
					"rot": [0.999846,-0.00888138,-0.0151253,0.000134354]
				},
				"leftArm": {
					"pos": [6.61962,-0.47182,10.1414],
					"rot": [0.997995,-0.0278282,-0.0568495,-0.000574873]
				},
				"leftHand": {
					"pos": [6.73306,-0.52743,9.14946],
					"rot": [0.997679,-0.0278309,-0.0621372,-0.000427401]
				},
				"leftThumb1": {
					"pos": [5.85181,-3.58097,8.20116],
					"rot": [0.999252,-0.0276825,0.0268495,-0.00290117]
				},
				"leftThumb2": {
					"pos": [5.73986,-4.68976,6.26259],
					"rot": [0.967709,0.25062,0.0249908,-0.010236]
				},
				"leftFinger11": {
					"pos": [8.95692,-2.63029,7.52698],
					"rot": [0.997027,-0.0538298,-0.0550901,-0.00205941]
				},
				"leftFinger12": {
					"pos": [9.17618,-2.84542,5.55071],
					"rot": [0.996685,-0.0532273,0.0609654,-0.00829128]
				},
				"leftFinger21": {
					"pos": [8.96554,-0.63339,7.41602],
					"rot": [0.998951,-0.0276536,0.036362,-0.0031646]
				},
				"leftFinger22": {
					"pos": [8.81989,-0.743428,5.42437],
					"rot": [0.982797,-0.0268897,0.182582,-0.00718898]
				},
				"leftFinger31": {
					"pos": [8.97416,1.36351,7.30506],
					"rot": [0.990621,0.0426589,0.128953,-0.0148601]
				},
				"leftFinger32": {
					"pos": [8.46572,1.54021,5.37886],
					"rot": [0.952167,0.0446154,0.302222,-0.00707645]
				},
				"offHand": {
					"pos": [7.10495,-0.694187,6.17727],
					"rot": [0.997679,-0.0278309,-0.0621372,-0.000427401]
				},
				"rightShoulder": {
					"pos": [-3.5,0.0975129,14.0394],
					"rot": [0.999925,-0.0050625,0.0111285,-0.000141364]
				},
				"rightArm": {
					"pos": [-6.58837,-0.44176,10.1124],
					"rot": [0.998659,-0.0165746,0.0490512,0.000232546]
				},
				"rightHand": {
					"pos": [-6.68633,-0.474887,9.11775],
					"rot": [0.998334,-0.0165757,0.0552601,0.000129478]
				},
				"rightThumb1": {
					"pos": [-5.7965,-3.50792,8.11332],
					"rot": [0.999127,-0.0164909,-0.0383436,0.00167903]
				},
				"rightThumb2": {
					"pos": [-5.64106,-4.57302,6.15337],
					"rot": [0.948522,0.314378,-0.0356381,0.0142471]
				},
				"rightFinger11": {
					"pos": [-8.8906,-2.53686,7.41791],
					"rot": [0.998148,-0.0504265,0.0339858,0.00163463]
				},
				"rightFinger12": {
					"pos": [-9.02596,-2.73842,5.4327],
					"rot": [0.989144,-0.0493958,-0.138018,0.0102744]
				},
				"rightFinger21": {
					"pos": [-8.89478,-0.537961,7.35175],
					"rot": [0.998406,-0.0164627,-0.0539487,0.00193647]
				},
				"rightFinger22": {
					"pos": [-8.6792,-0.603289,5.36447],
					"rot": [0.949842,-0.0153891,-0.312289,0.00616006]
				},
				"rightFinger31": {
					"pos": [-8.89896,1.46094,7.28558],
					"rot": [0.992836,0.0461177,-0.110205,-0.0020864]
				},
				"rightFinger32": {
					"pos": [-8.46091,1.64317,5.34267],
					"rot": [0.932721,0.044092,-0.357632,-0.013678]
				},
				"mainHand": {
					"pos": [-7.01733,-0.574219,6.13772],
					"rot": [0.998334,-0.0165757,0.0552601,0.000129478]
				},
				"leftFoot": {
					"pos": [3,-1.5,5],
					"rot": [1.0,0.0,0.0,0.0]
				},
				"rightFoot": {
					"pos": [-3,-1.5,5],
					"rot": [1.0,0.0,0.0,0.0]
				}
			},
			{
				"root": {
					"pos": [0,0,0],
					"rot": [1.0,0.0,0.0,0.0]
				},
				"bodyPosition": {
					"pos": [0,0,7.5],
					"rot": [1.0,0.0,0.0,0.0]
				},
				"pelvis": {
					"pos": [0,0,7.5],
					"rot": [1.0,0.0,0.0,0.0]
				},
				"torso": {
					"pos": [0,0,10],
					"rot": [1.0,0.0,0.0,0.0]
				},
				"head": {
					"pos": [0,-1.02572,16.9696],
					"rot": [1.0,0.0,0.0,0.0]
				},
				"leftShoulder": {
					"pos": [3.5,0,14],
					"rot": [1.0,0.0,0.0,0.0]
				},
				"leftArm": {
					"pos": [6.5,-0.5,10],
					"rot": [0.999105,0.0,-0.0422948,0.0]
				},
				"leftHand": {
					"pos": [6.58451,-0.5,9.00358],
					"rot": [0.999105,0.0,-0.0422948,0.0]
				},
				"leftThumb1": {
					"pos": [5.67261,-3.5,7.92264],
					"rot": [0.998907,0.0,0.0467401,0.0]
				},
				"leftThumb2": {
					"pos": [5.48585,-4.5,5.93138],
					"rot": [0.955777,0.290354,0.044722,-0.013586]
				},
				"leftFinger11": {
					"pos": [8.74639,-2.5,7.17976],
					"rot": [0.999117,-0.0228376,-0.0352639,-0.000806057]
				},
				"leftFinger12": {
					"pos": [8.88724,-2.59138,5.18682],
					"rot": [0.995934,-0.0225678,0.0871425,-0.00359191]
				},
				"leftFinger21": {
					"pos": [8.74639,-0.5,7.17976],
					"rot": [0.998417,0.0,0.0562484,0.0]
				},
				"leftFinger22": {
					"pos": [8.52175,-0.5,5.19242],
					"rot": [0.977844,0.0,0.209337,0.0]
				},
				"leftFinger31": {
					"pos": [8.74639,1.5,7.17976],
					"rot": [0.986455,0.0676568,0.149079,-0.0102247]
				},
				"leftFinger32": {
					"pos": [8.16092,1.77306,5.28697],
					"rot": [0.94048,0.0683697,0.332891,0.002751]
				},
				"offHand": {
					"pos": [6.83806,-0.5,6.01431],
					"rot": [0.999105,0.0,-0.0422948,0.0]
				},
				"rightShoulder": {
					"pos": [-3.5,0,14],
					"rot": [1.0,0.0,0.0,0.0]
				},
				"rightArm": {
					"pos": [-6.5,-0.5,10],
					"rot": [0.99928,0.0,0.037933,0.0]
				},
				"rightHand": {
					"pos": [-6.57581,-0.5,9.00288],
					"rot": [0.99928,0.0,0.037933,0.0]
				},
				"rightThumb1": {
					"pos": [-5.6545,-3.5,7.92995],
					"rot": [0.998449,0.0,-0.0556832,0.0]
				},
				"rightThumb2": {
					"pos": [-5.43211,-4.5,5.94235],
					"rot": [0.935209,0.349692,-0.0521563,0.0195022]
				},
				"rightFinger11": {
					"pos": [-8.72168,-2.5,7.16026],
					"rot": [0.999375,-0.0311734,0.0166704,0.000519997]
				},
				"rightFinger12": {
					"pos": [-8.78825,-2.62465,5.16526],
					"rot": [0.985427,-0.0305473,-0.167214,0.00623819]
				},
				"rightFinger21": {
					"pos": [-8.72168,-0.5,7.16026],
					"rot": [0.997457,0.0,-0.0712756,0.0]
				},
				"rightFinger22": {
					"pos": [-8.4373,-0.5,5.18058],
					"rot": [0.939516,0.0,-0.342506,0.0]
				},
				"rightFinger31": {
					"pos": [-8.72168,1.5,7.16026],
					"rot": [0.989873,0.0624973,-0.1274,-0.00386322]
				},
				"rightFinger32": {
					"pos": [-8.21627,1.74549,5.2408],
					"rot": [0.918828,0.0591392,-0.38966,-0.0205764]
				},
				"mainHand": {
					"pos": [-6.80324,-0.5,6.01151],
					"rot": [0.99928,0.0,0.037933,0.0]
				},
				"leftFoot": {
					"pos": [3,-1.5,5],
					"rot": [1.0,0.0,0.0,0.0]
				},
				"rightFoot": {
					"pos": [-3,-1.5,5],
					"rot": [1.0,0.0,0.0,0.0]
				}
			}
	]
}
