{
   "type": "entity",
   "mixins" : "stonehearth:mixins:item_properties",
   "components" : {
      "unit_info" : {
      },
      "render_info" : {
      },
      "model_variants": {
         "default": {
            "layer": "clothing",
            "models": [
               "file(footman_outfit.qb)"
            ]
         },
         "female" : {
            "layer": "clothing",
            "models": [
               "file(footman_outfit_female.qb)"
            ]
         }
      },
      "stonehearth:equipment_piece" : {
         "render_type" : "merge_with_model",
         "injected_ai" : {
            "actions" : [
               "stonehearth:actions:patrol",
               "stonehearth:actions:patrol:idle",
               "stonehearth:actions:get_patrol_point",
               "stonehearth:actions:mark_patrol_complete"
            ],
            "observers" : [
               "stonehearth:observers:enemy_observer"
            ]            
         },
         "injected_commands" : [
         ]
      }
   }
}
