{
   "faction_name" : "Northern Alliance",
   "faction_id" : "northern_alliance",
   "surnames" : [
      "Finn",
      "Odilep",
      "Ketil",
      "Haft",
      "Sovi",
      "Guthrum",
      "Igurd",
      "Moror",
      "Erlinn",
      "Vemund"
   ],
   "given_names" : {
      "male" : [
         "Kiran",
         "Sel",
         "Jos",
         "Gurd",
         "Karr",
         "Skarf",
         "Valin",
         "Lovil",
         "Sineus",
         "Hakon"
      ],
      "female" : [
         "Geira",
         "Asta",
         "Olva",
         "Tovi",
         "Indunna",
         "Finna",
         "Jodis",
         "Mora",
         "Brynn",
         "Katla"
      ]
   }
}