{
   "type" : "entity",
   "extends" : "stonehearth.mixins.mob",
   "components" : {
      "radiant:ai" : {
         "actions" : [
            "stonehearth.actions.sleep_action",
            "stonehearth.actions.sleep_in_bed_action",
            "stonehearth.actions.grab_talisman_action"
         ]
      },
	   "unit_info" : {
		  "name": "Civilian",
		  "description": "Citizen of your town",
		  "faction": "civ"
	   },
	   "attributes" : {
		  "ferocity": 1,
		  "health": 50
	   },
      "carry_block": {
      },
      "stonehearth:bed_lease" : {
      }
	}
}

