{
	"materials" : {
		"SELECTABLE" : {
			"name" : "materials/selected.material.json",
			"inputs" : [
				{
					"name" : "selected_color_fast",
					"bind_to_material_input" : "selected_color_fast"
				},
				{
					"name" : "selected_color",
					"bind_to_material_input" : "selected_color"
				}
			]
		}
	},

	"shaders" : {
		"DEPTH": {
			"state" : "states/voxel/replace.state",
			"shader" : "shaders/voxel/flat_color.shader",
			"inputs" : [
				{
					"name" : "flat_color",
					"default" : [0, 0, 0, 1]
				}
			]
		},

		"FOG": {
			"state" : "states/voxel/blend.state",
			"shader" : "shaders/voxel/fog.shader"
		},

		"DIRECTIONAL_SHADOWMAP": {
			"state" : "states/voxel/replace.state",
			"shader" : "shaders/voxel/flat_color.shader",
			"inputs" : [
				{
					"name" : "flat_color",
					"default" : [0, 0, 0, 0]
				}
			]
		},

		"OMNI_SHADOWMAP" : {
			"state" : "states/voxel/replace.state",
			"shader" : "shaders/voxel/omni_shadowmap.shader"
		},

		"OMNI_LIGHTING_FORWARD" : {
			"state" : "states/voxel/add.state",
			"shader" : "shaders/voxel/omni_lighting_f.shader"
		},

		"OMNI_LIGHTING_NO_SHADOW_FORWARD" : {
			"state" : "states/voxel/add.state",
			"shader" : "shaders/voxel/omni_lighting_noshadow_f.shader"
		},

		"DIRECTIONAL_LIGHTING_FORWARD" : {
			"state" : "states/voxel/add.state",
			"shader" : "shaders/voxel/dir_lighting_f.shader",
			"inputs" : [
				{
					"name" : "gridlineColor",
					"default" : [0.2, 0.2, 0.2, 1.0],
					"bind_to_material_input" : "gridlineColor"
				}
			]
		},

		"DEPTH_LINEAR" : {
			"state" : "states/voxel/replace.state",
			"shader" : "shaders/voxel/depth_linear.shader"
		},
		
		"DEPTH_LINEAR_BACK" : {
			"state" : "states/voxel/depth_back_mask.state",
			"shader" : "shaders/voxel/depth_back.shader"
		},
		
		"BLOOM" : {
			"state" : "states/voxel/replace.state",
			"shader" : "shaders/voxel/flat_color.shader",
			"inputs" : [
				{
					"name" : "flat_color",
					"default" : [0.0, 0.0, 0.0, 0.0]
				}
			]
		},

		"DEFERRED_ATTRIBUTES" : {
			"state" : "states/voxel/replace_mask.state",
			"shader" : "shaders/voxel/deferred_attributes.shader",
			"inputs" : [
				{
					"name" : "gridlineColor",
					"default" : [0.2, 0.2, 0.2, 1.0],
					"bind_to_material_input" : "gridlineColor"
				},
				{
					"name" : "glossy",
					"default" : [0.0, 0.0, 0.0, 0.0],
					"bind_to_material_input" : "glossy"
				}
			]
		},
		"DEFERRED_ALBEDO_LOD" : {
			"state" : "states/voxel/add.state",
			"shader" : "shaders/voxel/deferred_albedo_lod.shader",
			"inputs" : [
				{
					"name" : "gridlineColor",
					"default" : [0.2, 0.2, 0.2, 1.0],
					"bind_to_material_input" : "gridlineColor"
				}
			]
		}
	},

	"inputs" : [
		{
			"name" : "glossy",
			"default" : [0.0, 0.0, 0.0, 0.0]
		},
		{
			"name" : "gridlineColor",
			"default" : [0.2, 0.2, 0.2, 0.0]
		},
		{
			"name" : "selected_color_fast",
			"default" : [0.4, 0.4, 0.4, 1.0]
		},
		{
			"name" : "selected_color",
			"default" : [0.9, 0.9, 0.9, 1]
		}
	]
}
