{
	"type": "animation",
	"frames": [
			{
				"root": {
					"pos": [0,0,2.36588e-007],
					"rot": [1.0,0.0,0.0,0.0]
				},
				"torso": {
					"pos": [0.5,0.5,5],
					"rot": [0.998256,0.0590326,0.0,0.0]
				},
				"leftBackLeg": {
					"pos": [1.5,2.54766,4.69873],
					"rot": [0.992968,-0.118383,0.0,0.0]
				},
				"leftBackPaw": {
					"pos": [1.5,2.44654,2.19998],
					"rot": [0.964092,-0.265567,0.0,0.0]
				},
				"rightBackLeg": {
					"pos": [-1.5,2.54766,4.69873],
					"rot": [0.992968,-0.118383,0.0,0.0]
				},
				"rightBackPaw": {
					"pos": [-1.5,2.44654,2.19998],
					"rot": [0.964092,-0.265567,0.0,0.0]
				},
				"rightFrontLeg": {
					"pos": [-1.5,-1.86732,3.73425],
					"rot": [0.998256,0.0590326,0.0,0.0]
				},
				"rightFrontPaw": {
					"pos": [-1.5,-1.50063,0.734478],
					"rot": [0.998352,0.0573836,0.0,0.0]
				},
				"leftFrontLeg": {
					"pos": [1.5,-1.86732,3.73425],
					"rot": [0.998256,0.0590326,0.0,0.0]
				},
				"leftFrontPaw": {
					"pos": [1.5,-1.50063,0.734478],
					"rot": [0.998256,0.0590326,0.0,0.0]
				},
				"tail0": {
					"pos": [0,3.91612,5.90896],
					"rot": [0.920928,0.389733,0.0,0.0]
				},
				"tail1": {
					"pos": [0,5.30855,7.34462],
					"rot": [0.558069,0.829795,0.0,0.0]
				},
				"head": {
					"pos": [0,-2.01483,4.71337],
					"rot": [0.998256,0.0590326,0.0,0.0]
				}
			},
			{
				"root": {
					"pos": [0,0,2.36588e-007],
					"rot": [1.0,0.0,0.0,0.0]
				},
				"torso": {
					"pos": [0.5,0.5,4.9897],
					"rot": [0.998789,0.0492031,0.0,0.0]
				},
				"leftBackLeg": {
					"pos": [1.5,2.54133,4.64817],
					"rot": [0.990701,-0.136057,0.0,0.0]
				},
				"leftBackPaw": {
					"pos": [1.5,2.35125,2.15461],
					"rot": [0.974275,-0.225361,0.0,0.0]
				},
				"rightBackLeg": {
					"pos": [-1.5,2.54133,4.64817],
					"rot": [0.990701,-0.136057,0.0,0.0]
				},
				"rightBackPaw": {
					"pos": [-1.5,2.35125,2.15461],
					"rot": [0.974426,-0.224708,0.0,0.0]
				},
				"rightFrontLeg": {
					"pos": [-1.5,-1.89178,3.77079],
					"rot": [0.998163,0.0605883,0.0,0.0]
				},
				"rightFrontPaw": {
					"pos": [-1.5,-1.51574,0.77218],
					"rot": [0.991095,0.133158,0.0,0.0]
				},
				"leftFrontLeg": {
					"pos": [1.5,-1.89178,3.77079],
					"rot": [0.998163,0.0605883,0.0,0.0]
				},
				"leftFrontPaw": {
					"pos": [1.5,-1.51574,0.77218],
					"rot": [0.990908,0.134539,0.0,0.0]
				},
				"tail0": {
					"pos": [0,3.93335,5.83122],
					"rot": [0.927594,0.373589,7.84862e-006,2.68461e-005]
				},
				"tail1": {
					"pos": [-8.78805e-005,5.37508,7.21738],
					"rot": [0.573444,0.819245,2.12268e-005,1.82137e-005]
				},
				"head": {
					"pos": [0,-2.02123,4.76524],
					"rot": [0.998142,0.0609307,0.0,0.0]
				}
			},
			{
				"root": {
					"pos": [0,0,2.36588e-007],
					"rot": [1.0,0.0,0.0,0.0]
				},
				"torso": {
					"pos": [0.5,0.5,4.96702],
					"rot": [0.99962,0.0275629,0.0,0.0]
				},
				"leftBackLeg": {
					"pos": [1.5,2.52463,4.53743],
					"rot": [0.984607,-0.17478,0.0,0.0]
				},
				"leftBackPaw": {
					"pos": [1.5,2.13982,2.06642],
					"rot": [0.990758,-0.135641,0.0,0.0]
				},
				"rightBackLeg": {
					"pos": [-1.5,2.52463,4.53743],
					"rot": [0.984607,-0.17478,0.0,0.0]
				},
				"rightBackPaw": {
					"pos": [-1.5,2.13982,2.06642],
					"rot": [0.991046,-0.133517,0.0,0.0]
				},
				"rightFrontLeg": {
					"pos": [-1.5,-1.94231,3.85283],
					"rot": [0.997724,0.0674238,0.0,0.0]
				},
				"rightFrontPaw": {
					"pos": [-1.5,-1.52524,0.859648],
					"rot": [0.954002,0.299801,0.0,0.0]
				},
				"leftFrontLeg": {
					"pos": [1.5,-1.94231,3.85283],
					"rot": [0.997724,0.0674238,0.0,0.0]
				},
				"leftFrontPaw": {
					"pos": [1.5,-1.52524,0.859648],
					"rot": [0.953754,0.300588,0.0,0.0]
				},
				"tail0": {
					"pos": [0,3.96657,5.6591],
					"rot": [0.942578,0.333987,2.92485e-005,9.96858e-005]
				},
				"tail1": {
					"pos": [-0.000336772,5.52038,6.91833],
					"rot": [0.610154,0.792283,7.86907e-005,6.7827e-005]
				},
				"head": {
					"pos": [0,-2.03048,4.88627],
					"rot": [0.997878,0.0651057,0.0,0.0]
				}
			},
			{
				"root": {
					"pos": [0,0,2.36588e-007],
					"rot": [1.0,0.0,0.0,0.0]
				},
				"torso": {
					"pos": [0.5,0.5,4.94435],
					"rot": [0.999983,0.00590983,0.0,0.0]
				},
				"leftBackLeg": {
					"pos": [1.5,2.50413,4.4275],
					"rot": [0.977001,-0.213235,0.0,0.0]
				},
				"leftBackPaw": {
					"pos": [1.5,1.92696,1.99422],
					"rot": [0.998996,-0.0447921,0.0,0.0]
				},
				"rightBackLeg": {
					"pos": [-1.5,2.50413,4.4275],
					"rot": [0.977001,-0.213235,0.0,0.0]
				},
				"rightBackPaw": {
					"pos": [-1.5,1.92696,1.99422],
					"rot": [0.999152,-0.0411788,0.0,0.0]
				},
				"rightFrontLeg": {
					"pos": [-1.5,-1.98827,3.93695],
					"rot": [0.996568,0.0827815,0.0,0.0]
				},
				"rightFrontPaw": {
					"pos": [-1.5,-1.4792,0.958038],
					"rot": [0.885157,0.465292,0.0,0.0]
				},
				"leftFrontLeg": {
					"pos": [1.5,-1.98827,3.93695],
					"rot": [0.996568,0.0827815,0.0,0.0]
				},
				"leftFrontPaw": {
					"pos": [1.5,-1.4792,0.958038],
					"rot": [0.885037,0.46552,0.0,0.0]
				},
				"tail0": {
					"pos": [0,3.99329,5.48568],
					"rot": [0.958704,0.284404,5.89159e-005,0.000207568]
				},
				"tail1": {
					"pos": [-0.000728962,5.66974,6.57632],
					"rot": [0.6542,0.756322,0.00016151,0.000143074]
				},
				"head": {
					"pos": [0,-2.0322,5.0239],
					"rot": [0.997597,0.0692795,0.0,0.0]
				}
			},
			{
				"root": {
					"pos": [0,0,2.36588e-007],
					"rot": [1.0,0.0,0.0,0.0]
				},
				"torso": {
					"pos": [0.5,0.5,4.93405],
					"rot": [0.999992,-0.00393402,0.0,0.0]
				},
				"leftBackLeg": {
					"pos": [1.5,2.49356,4.37784],
					"rot": [0.973046,-0.23061,0.0,0.0]
				},
				"leftBackPaw": {
					"pos": [1.5,1.83007,1.96667],
					"rot": [0.999994,-0.00332834,0.0,0.0]
				},
				"rightBackLeg": {
					"pos": [-1.5,2.49356,4.37784],
					"rot": [0.973046,-0.23061,0.0,0.0]
				},
				"rightBackPaw": {
					"pos": [-1.5,1.83007,1.96667],
					"rot": [1.0,0.000957981,0.0,0.0]
				},
				"rightFrontLeg": {
					"pos": [-1.5,-2.00762,3.97583],
					"rot": [0.993946,0.109868,0.0,0.0]
				},
				"rightFrontPaw": {
					"pos": [-1.5,-1.33725,1.02902],
					"rot": [0.833292,0.552832,0.0,0.0]
				},
				"leftFrontLeg": {
					"pos": [1.5,-2.00762,3.97583],
					"rot": [0.993946,0.109868,0.0,0.0]
				},
				"leftFrontPaw": {
					"pos": [1.5,-1.33725,1.02902],
					"rot": [0.833292,0.552832,0.0,0.0]
				},
				"tail0": {
					"pos": [0,4.00326,5.4065],
					"rot": [0.970976,0.239178,8.67836e-005,0.000340743]
				},
				"tail1": {
					"pos": [-0.00124039,5.77444,6.33544],
					"rot": [0.693061,0.720879,0.000255386,0.000241693]
				},
				"head": {
					"pos": [0,-2.02966,5.12495],
					"rot": [0.997464,0.0711764,0.0,0.0]
				}
			},
			{
				"root": {
					"pos": [0,0,2.36588e-007],
					"rot": [1.0,0.0,0.0,0.0]
				},
				"torso": {
					"pos": [0.5,0.5,5.05509],
					"rot": [0.999994,-0.00357814,0.0,0.0]
				},
				"leftBackLeg": {
					"pos": [1.5,2.49396,4.5003],
					"rot": [0.981185,-0.19307,0.0,0.0]
				},
				"leftBackPaw": {
					"pos": [1.5,2.01748,2.04532],
					"rot": [0.999385,0.0350673,0.0,0.0]
				},
				"rightBackLeg": {
					"pos": [-1.5,2.49396,4.5003],
					"rot": [0.981185,-0.19307,0.0,0.0]
				},
				"rightBackPaw": {
					"pos": [-1.5,2.01748,2.04532],
					"rot": [0.999226,0.0393393,0.0,0.0]
				},
				"rightFrontLeg": {
					"pos": [-1.5,-2.00693,4.09509],
					"rot": [0.990362,0.138506,0.0,0.0]
				},
				"rightFrontPaw": {
					"pos": [-1.5,-1.16768,1.19186],
					"rot": [0.828769,0.559591,0.0,0.0]
				},
				"leftFrontLeg": {
					"pos": [1.5,-2.00693,4.09509],
					"rot": [0.990362,0.138506,0.0,0.0]
				},
				"leftFrontPaw": {
					"pos": [1.5,-1.16768,1.19186],
					"rot": [0.828781,0.559574,0.0,0.0]
				},
				"tail0": {
					"pos": [0,4.00293,5.53004],
					"rot": [0.97975,0.200224,0.000103503,0.00048862]
				},
				"tail1": {
					"pos": [-0.00183201,5.84257,6.31471],
					"rot": [0.725597,0.688119,0.000346274,0.000359939]
				},
				"head": {
					"pos": [0,-2.02931,5.31114],
					"rot": [0.998328,0.0578016,0.0,0.0]
				}
			},
			{
				"root": {
					"pos": [0,0,2.36588e-007],
					"rot": [1.0,0.0,0.0,0.0]
				},
				"torso": {
					"pos": [0.5,0.5,5.3577],
					"rot": [0.999997,-0.00244978,0.0,0.0]
				},
				"leftBackLeg": {
					"pos": [1.5,2.49521,4.80741],
					"rot": [0.9952,-0.0978593,0.0,0.0]
				},
				"leftBackPaw": {
					"pos": [1.5,2.49732,2.30662],
					"rot": [0.991397,0.130892,0.0,0.0]
				},
				"rightBackLeg": {
					"pos": [-1.5,2.49521,4.80741],
					"rot": [0.9952,-0.0978593,0.0,0.0]
				},
				"rightBackPaw": {
					"pos": [-1.5,2.49732,2.30662],
					"rot": [0.990839,0.135051,0.0,0.0]
				},
				"rightFrontLeg": {
					"pos": [-1.5,-2.00476,4.39204],
					"rot": [0.988548,0.150904,0.0,0.0]
				},
				"rightFrontPaw": {
					"pos": [-1.5,-1.09302,1.51076],
					"rot": [0.851062,0.525065,0.0,0.0]
				},
				"leftFrontLeg": {
					"pos": [1.5,-2.00476,4.39204],
					"rot": [0.988548,0.150904,0.0,0.0]
				},
				"leftFrontPaw": {
					"pos": [1.5,-1.09302,1.51076],
					"rot": [0.851097,0.525008,0.0,0.0]
				},
				"tail0": {
					"pos": [0,4.00185,5.84055],
					"rot": [0.986838,0.161713,0.000107806,0.000638262]
				},
				"tail1": {
					"pos": [-0.00244971,5.89724,6.47889],
					"rot": [0.756082,0.654477,0.000426038,0.000487332]
				},
				"head": {
					"pos": [0,-2.02956,5.67498],
					"rot": [0.999698,0.0245631,0.0,0.0]
				}
			},
			{
				"root": {
					"pos": [0,0,2.36588e-007],
					"rot": [1.0,0.0,0.0,0.0]
				},
				"torso": {
					"pos": [0.5,0.5,5.7511],
					"rot": [1.0,-0.000457901,0.0,0.0]
				},
				"leftBackLeg": {
					"pos": [1.5,2.49738,5.20876],
					"rot": [0.999617,0.0276616,0.0,0.0]
				},
				"leftBackPaw": {
					"pos": [1.5,3.12144,2.78708],
					"rot": [0.967224,0.253924,0.0,0.0]
				},
				"rightBackLeg": {
					"pos": [-1.5,2.49738,5.20876],
					"rot": [0.999617,0.0276616,0.0,0.0]
				},
				"rightBackPaw": {
					"pos": [-1.5,3.12144,2.78708],
					"rot": [0.966205,0.257773,0.0,0.0]
				},
				"rightFrontLeg": {
					"pos": [-1.5,-2.00089,4.77546],
					"rot": [0.996537,0.0831542,0.0,0.0]
				},
				"rightFrontPaw": {
					"pos": [-1.5,-1.4896,1.79693],
					"rot": [0.916778,0.399397,0.0,0.0]
				},
				"leftFrontLeg": {
					"pos": [1.5,-2.00089,4.77546],
					"rot": [0.996537,0.0831542,0.0,0.0]
				},
				"leftFrontPaw": {
					"pos": [1.5,-1.4896,1.79693],
					"rot": [0.916823,0.399294,0.0,0.0]
				},
				"tail0": {
					"pos": [0,3.9999,6.24789],
					"rot": [0.991896,0.127052,0.000100213,0.000776718]
				},
				"tail1": {
					"pos": [-0.00303076,5.93532,6.75198],
					"rot": [0.782127,0.623119,0.00048856,0.00061208]
				},
				"head": {
					"pos": [0,-2.03074,6.11982],
					"rot": [0.999835,-0.0181571,0.0,0.0]
				}
			},
			{
				"root": {
					"pos": [0,0,2.36588e-007],
					"rot": [1.0,0.0,0.0,0.0]
				},
				"torso": {
					"pos": [0.5,0.5,6.14449],
					"rot": [0.999997,0.00248854,0.0,0.0]
				},
				"leftBackLeg": {
					"pos": [1.5,2.50054,5.61393],
					"rot": [0.988119,0.153689,0.0,0.0]
				},
				"leftBackPaw": {
					"pos": [1.5,3.7115,3.42588],
					"rot": [0.927566,0.373659,0.0,0.0]
				},
				"rightBackLeg": {
					"pos": [-1.5,2.50054,5.61393],
					"rot": [0.988119,0.153689,0.0,0.0]
				},
				"rightBackPaw": {
					"pos": [-1.5,3.7115,3.42588],
					"rot": [0.926228,0.376964,0.0,0.0]
				},
				"rightFrontLeg": {
					"pos": [-1.5,-1.9951,5.15414],
					"rot": [0.997669,-0.0682443,0.0,0.0]
				},
				"rightFrontPaw": {
					"pos": [-1.5,-2.39614,2.15877],
					"rot": [0.984132,0.177436,0.0,0.0]
				},
				"leftFrontLeg": {
					"pos": [1.5,-1.9951,5.15414],
					"rot": [0.997669,-0.0682443,0.0,0.0]
				},
				"leftFrontPaw": {
					"pos": [1.5,-2.39614,2.15877],
					"rot": [0.984156,0.177305,0.0,0.0]
				},
				"tail0": {
					"pos": [0,3.99691,6.6619],
					"rot": [0.995018,0.0996878,8.47906e-005,0.000891011]
				},
				"tail1": {
					"pos": [-0.00351248,5.95715,7.05866],
					"rot": [0.801822,0.597562,0.000531261,0.000720313]
				},
				"head": {
					"pos": [0,-2.03312,6.54895],
					"rot": [0.998205,-0.0598914,0.0,0.0]
				}
			},
			{
				"root": {
					"pos": [0,0,2.36588e-007],
					"rot": [1.0,0.0,0.0,0.0]
				},
				"torso": {
					"pos": [0.5,0.5,6.4471],
					"rot": [0.999979,0.00648053,0.0,0.0]
				},
				"leftBackLeg": {
					"pos": [1.5,2.50472,5.93253],
					"rot": [0.968056,0.250734,0.0,0.0]
				},
				"leftBackPaw": {
					"pos": [1.5,4.12294,4.02588],
					"rot": [0.886349,0.463018,0.0,0.0]
				},
				"rightBackLeg": {
					"pos": [-1.5,2.50472,5.93253],
					"rot": [0.968056,0.250734,0.0,0.0]
				},
				"rightBackPaw": {
					"pos": [-1.5,4.12294,4.02588],
					"rot": [0.885013,0.465566,0.0,0.0]
				},
				"rightFrontLeg": {
					"pos": [-1.5,-1.98712,5.43686],
					"rot": [0.976159,-0.217058,0.0,0.0]
				},
				"rightFrontPaw": {
					"pos": [-1.5,-3.25819,2.69506],
					"rot": [0.998874,-0.0474318,0.0,0.0]
				},
				"leftFrontLeg": {
					"pos": [1.5,-1.98712,5.43686],
					"rot": [0.976159,-0.217058,0.0,0.0]
				},
				"leftFrontPaw": {
					"pos": [1.5,-3.25819,2.69506],
					"rot": [0.998869,-0.047536,0.0,0.0]
				},
				"tail0": {
					"pos": [0,3.99266,6.99241],
					"rot": [0.996544,0.0830612,6.8101e-005,0.000968563]
				},
				"tail1": {
					"pos": [-0.00383823,5.96506,7.32351],
					"rot": [0.813555,0.581487,0.000554312,0.000797176]
				},
				"head": {
					"pos": [0,-2.03672,6.8657],
					"rot": [0.995923,-0.090209,0.0,0.0]
				}
			},
			{
				"root": {
					"pos": [0,0,2.36588e-007],
					"rot": [1.0,0.0,0.0,0.0]
				},
				"torso": {
					"pos": [0.5,0.5,6.56814],
					"rot": [0.999933,0.011609,0.0,0.0]
				},
				"leftBackLeg": {
					"pos": [1.5,2.50989,6.07416],
					"rot": [0.956328,0.292295,0.0,0.0]
				},
				"leftBackPaw": {
					"pos": [1.5,4.28656,4.31422],
					"rot": [0.866049,0.499959,0.0,0.0]
				},
				"rightBackLeg": {
					"pos": [-1.5,2.50989,6.07416],
					"rot": [0.956328,0.292295,0.0,0.0]
				},
				"rightBackPaw": {
					"pos": [-1.5,4.28656,4.31422],
					"rot": [0.865122,0.501562,0.0,0.0]
				},
				"rightFrontLeg": {
					"pos": [-1.5,-1.97662,5.53244],
					"rot": [0.959972,-0.280097,0.0,0.0]
				},
				"rightFrontPaw": {
					"pos": [-1.5,-3.59289,2.97887],
					"rot": [0.98568,-0.168626,0.0,0.0]
				},
				"leftFrontLeg": {
					"pos": [1.5,-1.97662,5.53244],
					"rot": [0.959972,-0.280097,0.0,0.0]
				},
				"leftFrontPaw": {
					"pos": [1.5,-3.59289,2.97887],
					"rot": [0.98568,-0.168626,0.0,0.0]
				},
				"tail0": {
					"pos": [0,3.98689,7.14925],
					"rot": [0.996748,0.0805761,5.73517e-005,0.000997276]
				},
				"tail1": {
					"pos": [-0.00395765,5.96091,7.47051],
					"rot": [0.815686,0.578493,0.000558798,0.000828005]
				},
				"head": {
					"pos": [0,-2.04117,6.97336],
					"rot": [0.995107,-0.0988003,0.0,0.0]
				}
			},
			{
				"root": {
					"pos": [0,0,2.36588e-007],
					"rot": [1.0,0.0,0.0,0.0]
				},
				"torso": {
					"pos": [0.5,0.5,6.40506],
					"rot": [0.999796,0.020209,0.0,0.0]
				},
				"leftBackLeg": {
					"pos": [1.5,2.51809,5.94572],
					"rot": [0.967131,0.254278,0.0,0.0]
				},
				"leftBackPaw": {
					"pos": [1.5,4.15024,4.05098],
					"rot": [0.903028,0.429582,0.0,0.0]
				},
				"rightBackLeg": {
					"pos": [-1.5,2.51809,5.94572],
					"rot": [0.967131,0.254278,0.0,0.0]
				},
				"rightBackPaw": {
					"pos": [-1.5,4.15024,4.05098],
					"rot": [0.90265,0.430376,0.0,0.0]
				},
				"rightFrontLeg": {
					"pos": [-1.5,-1.95844,5.32691],
					"rot": [0.970244,-0.242131,0.0,0.0]
				},
				"rightFrontPaw": {
					"pos": [-1.5,-3.36903,2.65421],
					"rot": [0.985593,-0.169132,0.0,0.0]
				},
				"leftFrontLeg": {
					"pos": [1.5,-1.95844,5.32691],
					"rot": [0.970244,-0.242131,0.0,0.0]
				},
				"leftFrontPaw": {
					"pos": [1.5,-3.36903,2.65421],
					"rot": [0.985639,-0.168868,0.0,0.0]
				},
				"tail0": {
					"pos": [0,3.97638,7.04606],
					"rot": [0.993096,0.117305,6.89878e-005,0.000892373]
				},
				"tail1": {
					"pos": [-0.00351248,5.92133,7.51204],
					"rot": [0.791107,0.611677,0.000518413,0.000729614]
				},
				"head": {
					"pos": [0,-2.04588,6.71989],
					"rot": [0.996892,-0.0787796,0.0,0.0]
				}
			},
			{
				"root": {
					"pos": [0,0,2.36588e-007],
					"rot": [1.0,0.0,0.0,0.0]
				},
				"torso": {
					"pos": [0.5,0.5,6.01616],
					"rot": [0.999474,0.0324324,0.0,0.0]
				},
				"leftBackLeg": {
					"pos": [1.5,2.52872,5.60631],
					"rot": [0.988078,0.153954,0.0,0.0]
				},
				"leftBackPaw": {
					"pos": [1.5,3.74084,3.41891],
					"rot": [0.969433,0.245358,0.0,0.0]
				},
				"rightBackLeg": {
					"pos": [-1.5,2.52872,5.60631],
					"rot": [0.988078,0.153954,0.0,0.0]
				},
				"rightBackPaw": {
					"pos": [-1.5,3.74084,3.41891],
					"rot": [0.969353,0.245671,0.0,0.0]
				},
				"rightFrontLeg": {
					"pos": [-1.5,-1.93134,4.87821],
					"rot": [0.987378,-0.158379,0.0,0.0]
				},
				"rightFrontPaw": {
					"pos": [-1.5,-2.86648,2.00444],
					"rot": [0.993198,-0.116439,0.0,0.0]
				},
				"leftFrontLeg": {
					"pos": [1.5,-1.93134,4.87821],
					"rot": [0.987378,-0.158379,0.0,0.0]
				},
				"leftFrontPaw": {
					"pos": [1.5,-2.86648,2.00444],
					"rot": [0.993278,-0.115754,0.0,0.0]
				},
				"tail0": {
					"pos": [0,3.95966,6.74198],
					"rot": [0.980596,0.196036,8.54769e-005,0.000641634]
				},
				"tail1": {
					"pos": [-0.00244971,5.80594,7.5109],
					"rot": [0.732793,0.680452,0.00040878,0.000501896]
				},
				"head": {
					"pos": [0,-2.0456,6.15747],
					"rot": [0.999231,-0.0392019,0.0,0.0]
				}
			},
			{
				"root": {
					"pos": [0,0,2.36588e-007],
					"rot": [1.0,0.0,0.0,0.0]
				},
				"torso": {
					"pos": [0.5,0.5,5.55199],
					"rot": [0.998983,0.0450956,0.0,0.0]
				},
				"leftBackLeg": {
					"pos": [1.5,2.53845,5.19368],
					"rot": [0.999542,0.0302645,0.0,0.0]
				},
				"leftBackPaw": {
					"pos": [1.5,3.17511,2.77529],
					"rot": [0.999925,0.0122738,0.0,0.0]
				},
				"rightBackLeg": {
					"pos": [-1.5,2.53845,5.19368],
					"rot": [0.999542,0.0302645,0.0,0.0]
				},
				"rightBackPaw": {
					"pos": [-1.5,3.17511,2.77529],
					"rot": [0.999924,0.0123413,0.0,0.0]
				},
				"rightFrontLeg": {
					"pos": [-1.5,-1.90172,4.35279],
					"rot": [0.998266,-0.0588727,0.0,0.0]
				},
				"rightFrontPaw": {
					"pos": [-1.5,-2.24643,1.35042],
					"rot": [0.999179,-0.0405047,0.0,0.0]
				},
				"leftFrontLeg": {
					"pos": [1.5,-1.90172,4.35279],
					"rot": [0.998266,-0.0588727,0.0,0.0]
				},
				"leftFrontPaw": {
					"pos": [1.5,-2.24643,1.35042],
					"rot": [0.999225,-0.0393632,0.0,0.0]
				},
				"tail0": {
					"pos": [0,3.94016,6.36525],
					"rot": [0.958082,0.286493,6.99742e-005,0.000344588]
				},
				"tail1": {
					"pos": [-0.00124039,5.61184,7.46318],
					"rot": [0.656886,0.753989,0.00024323,0.000253923]
				},
				"head": {
					"pos": [0,-2.03635,5.49597],
					"rot": [0.999981,0.00618989,0.0,0.0]
				}
			},
			{
				"root": {
					"pos": [0,0,2.36588e-007],
					"rot": [1.0,0.0,0.0,0.0]
				},
				"torso": {
					"pos": [0.5,0.5,5.16309],
					"rot": [0.998485,0.0550199,0.0,0.0]
				},
				"leftBackLeg": {
					"pos": [1.5,2.54517,4.84536],
					"rot": [0.997222,-0.0744857,0.0,0.0]
				},
				"leftBackPaw": {
					"pos": [1.5,2.66458,2.34742],
					"rot": [0.982813,-0.184603,0.0,0.0]
				},
				"rightBackLeg": {
					"pos": [-1.5,2.54517,4.84536],
					"rot": [0.997222,-0.0744857,0.0,0.0]
				},
				"rightBackPaw": {
					"pos": [-1.5,2.66458,2.34742],
					"rot": [0.982813,-0.184605,0.0,0.0]
				},
				"rightFrontLeg": {
					"pos": [-1.5,-1.87742,3.9164],
					"rot": [0.999704,0.0243128,0.0,0.0]
				},
				"rightFrontPaw": {
					"pos": [-1.5,-1.71994,0.898412],
					"rot": [0.999614,0.0277926,0.0,0.0]
				},
				"leftFrontLeg": {
					"pos": [1.5,-1.87742,3.9164],
					"rot": [0.999704,0.0243128,0.0,0.0]
				},
				"leftFrontPaw": {
					"pos": [1.5,-1.71994,0.898412],
					"rot": [0.999571,0.029296,0.0,0.0]
				},
				"tail0": {
					"pos": [0,3.92332,6.04455],
					"rot": [0.933045,0.359761,2.64983e-005,0.000100452]
				},
				"tail1": {
					"pos": [-0.000336772,5.4056,7.38724],
					"rot": [0.588153,0.808749,7.67972e-005,6.99636e-005]
				},
				"head": {
					"pos": [0,-2.02239,4.94499],
					"rot": [0.999052,0.0435345,0.0,0.0]
				}
			},
			{
				"root": {
					"pos": [0,0,2.36588e-007],
					"rot": [1.0,0.0,0.0,0.0]
				},
				"torso": {
					"pos": [0.5,0.5,5],
					"rot": [0.998256,0.0590326,0.0,0.0]
				},
				"leftBackLeg": {
					"pos": [1.5,2.54766,4.69873],
					"rot": [0.992968,-0.118383,0.0,0.0]
				},
				"leftBackPaw": {
					"pos": [1.5,2.44654,2.19998],
					"rot": [0.964092,-0.265567,0.0,0.0]
				},
				"rightBackLeg": {
					"pos": [-1.5,2.54766,4.69873],
					"rot": [0.992968,-0.118383,0.0,0.0]
				},
				"rightBackPaw": {
					"pos": [-1.5,2.44654,2.19998],
					"rot": [0.964092,-0.265567,0.0,0.0]
				},
				"rightFrontLeg": {
					"pos": [-1.5,-1.86732,3.73425],
					"rot": [0.998256,0.0590326,0.0,0.0]
				},
				"rightFrontPaw": {
					"pos": [-1.5,-1.50063,0.734478],
					"rot": [0.998352,0.0573836,0.0,0.0]
				},
				"leftFrontLeg": {
					"pos": [1.5,-1.86732,3.73425],
					"rot": [0.998256,0.0590326,0.0,0.0]
				},
				"leftFrontPaw": {
					"pos": [1.5,-1.50063,0.734478],
					"rot": [0.998256,0.0590326,0.0,0.0]
				},
				"tail0": {
					"pos": [0,3.91612,5.90896],
					"rot": [0.920928,0.389733,0.0,0.0]
				},
				"tail1": {
					"pos": [0,5.30855,7.34462],
					"rot": [0.558069,0.829795,0.0,0.0]
				},
				"head": {
					"pos": [0,-2.01483,4.71337],
					"rot": [0.998256,0.0590326,0.0,0.0]
				}
			}
	]
}
