{
   "mixins": "stonehearth:mixins:item_properties",
   "type": "entity",
   "components": {
      "item": {
         "stacks": 10
      },
      "model_variants": {
         "default": {
            "models": [
               "file(cloth_bolt.qb)"
            ]
         }
      },
      "unit_info": {
         "name": "Bolt of Cloth",
         "description": "Shimmery.",
         "icon" : "file(cloth_bolt.png)"
      },
      "stonehearth:material" : {
         "tags" :  "cloth resource"
      }
   }
}