{
   "mixins": "stonehearth:mixins:item_properties",
   "type": "entity",
   "components": {
      "item": {
         "material": "stone",
         "category": "resources",
         "stacks": 10
      },
      "stonehearth:material" : {
         "tags" : "stone resource"
      },
      "model_variants": {
         "default": {
            "models": [
               "file(hunk_of_stone.qb)"
            ]
         }
      },
      "unit_info": {
         "name": "Hunk 'o Stone",
         "description": "A heavy, ordinary rock.",
         "icon" : "file(../stone.png)"
      }
   }
}